py.typed
orq_rc_poc/__init__.py
orq_rc_poc/_hooks/__init__.py
orq_rc_poc/_hooks/registration.py
orq_rc_poc/_hooks/sdkhooks.py
orq_rc_poc/_hooks/types.py
orq_rc_poc/_version.py
orq_rc_poc/basesdk.py
orq_rc_poc/contacts.py
orq_rc_poc/deployments_sdk.py
orq_rc_poc/feedback.py
orq_rc_poc/files.py
orq_rc_poc/httpclient.py
orq_rc_poc/langchain/__init__.py
orq_rc_poc/metrics.py
orq_rc_poc/models/__init__.py
orq_rc_poc/models/apierror.py
orq_rc_poc/models/bulkfileuploadop.py
orq_rc_poc/models/createcontactop.py
orq_rc_poc/models/createfeedbackop.py
orq_rc_poc/models/createpromptop.py
orq_rc_poc/models/createpromptversionop.py
orq_rc_poc/models/deletepromptop.py
orq_rc_poc/models/deploymentcreatemetricop.py
orq_rc_poc/models/deploymentgetconfigop.py
orq_rc_poc/models/deploymentinvokeop.py
orq_rc_poc/models/deployments.py
orq_rc_poc/models/deploymentsop.py
orq_rc_poc/models/duplicatepromptop.py
orq_rc_poc/models/fileuploadop.py
orq_rc_poc/models/findonepromptsnippetop.py
orq_rc_poc/models/getallpromptsop.py
orq_rc_poc/models/getallprompttemplatesop.py
orq_rc_poc/models/getonepromptop.py
orq_rc_poc/models/honoapierror.py
orq_rc_poc/models/invaliddeploymentop.py
orq_rc_poc/models/remoteconfigsgetconfigop.py
orq_rc_poc/models/security.py
orq_rc_poc/models/updatepromptop.py
orq_rc_poc/prompt.py
orq_rc_poc/prompts.py
orq_rc_poc/py.typed
orq_rc_poc/remoteconfig.py
orq_rc_poc/sdk.py
orq_rc_poc/sdkconfiguration.py
orq_rc_poc/snippets.py
orq_rc_poc/templates.py
orq_rc_poc/types/__init__.py
orq_rc_poc/types/basemodel.py
orq_rc_poc/utils/__init__.py
orq_rc_poc/utils/annotations.py
orq_rc_poc/utils/enums.py
orq_rc_poc/utils/eventstreaming.py
orq_rc_poc/utils/forms.py
orq_rc_poc/utils/headers.py
orq_rc_poc/utils/logger.py
orq_rc_poc/utils/metadata.py
orq_rc_poc/utils/queryparams.py
orq_rc_poc/utils/requestbodies.py
orq_rc_poc/utils/retries.py
orq_rc_poc/utils/security.py
orq_rc_poc/utils/serializers.py
orq_rc_poc/utils/url.py
orq_rc_poc/utils/values.py
orq_rc_poc-0.0.21.dist-info/METADATA
orq_rc_poc-0.0.21.dist-info/WHEEL
orq_rc_poc-0.0.21.dist-info/RECORD
